{"skeleton":{"hash":"8IMcY0KhLDCKw6w6q5mh7JDJBOo","spine":"3.8.79","x":-147.52,"y":-20.5,"width":293.34,"height":70.93,"images":"","audio":""},"bones":[{"name":"root"},{"name":"bone","parent":"root"},{"name":"Group 5","parent":"bone","x":5.56,"y":-4.63},{"name":"Group 6","parent":"bone","x":-7.67,"y":-3.82}],"slots":[{"name":"Group 5","bone":"Group 5","attachment":"Group 5"},{"name":"Group 6","bone":"Group 6","attachment":"Group 6"},{"name":"Layer 48","bone":"bone","attachment":"Layer 48"}],"skins":[{"name":"default","attachments":{"Group 5":{"Group 5":{"x":68.25,"y":22.3,"width":144,"height":65}},"Group 6":{"Group 6":{"x":-67.86,"y":21.75,"width":144,"height":65}},"Layer 48":{"Layer 48":{"width":58,"height":41}}}}],"animations":{"Attack":{"bones":{"Group 6":{"rotate":[{"curve":0.039,"c2":0.4,"c3":0.831,"c4":0.94},{"time":0.0667,"angle":-71.65}],"translate":[{}]},"Group 5":{"rotate":[{"curve":0.039,"c2":0.4,"c3":0.831,"c4":0.94},{"time":0.0667,"angle":70.89}],"translate":[{}]}}},"Idle":{}}}